{ "compressionlevel":-1,
 "height":10,
 "infinite":false,
 "layers":[
        {
         "data":[1, 19, 37, 1, 19, 37, 1, 19, 37, 1,
            19, 37, 1, 19, 37, 1, 19, 37, 1, 19,
            37, 1, 19, 37, 1, 19, 37, 1, 19, 39,
            1, 19, 37, 1, 19, 37, 1, 19, 37, 11,
            19, 37, 1, 19, 37, 1, 19, 37, 1, 19,
            37, 1, 19, 37, 1, 19, 37, 1, 19, 39,
            1, 19, 37, 1, 19, 37, 1, 19, 37, 11,
            19, 37, 1, 19, 37, 1, 19, 37, 1, 19,
            37, 1, 19, 37, 1, 19, 37, 1, 19, 39,
            1, 22, 54, 1, 22, 54, 1, 22, 54, 1],
         "height":10,
         "id":1,
         "name":"Tile Layer 1",
         "opacity":1,
         "type":"tilelayer",
         "visible":true,
         "width":10,
         "x":0,
         "y":0
        }],
 "nextlayerid":2,
 "nextobjectid":1,
 "orientation":"isometric",
 "renderorder":"right-down",
 "tiledversion":"1.9.2",
 "tileheight":32,
 "tilesets":[
        {
         "columns":6,
         "firstgid":1,
         "image":"..\/tilesets\/isometric-sandbox-sheet.png",
         "imageheight":576,
         "imagewidth":384,
         "margin":0,
         "name":"isometric-sandbox-sheet",
         "spacing":0,
         "tilecount":54,
         "tileheight":64,
         "tilewidth":64
        }],
 "tilewidth":64,
 "type":"map",
 "version":"1.9",
 "width":10
}